debcr/__init__.py
debcr/_core/__init__.py
debcr/_core/config.py
debcr/_core/data/__init__.py
debcr/_core/data/file_loaders.py
debcr/_core/data/file_writers.py
debcr/_core/data/process.py
debcr/_core/data/show.py
debcr/_core/model/__init__.py
debcr/_core/model/batchloader.py
debcr/_core/model/loss.py
debcr/_core/model/m_rBCR.py
debcr/_core/model/metrics.py
debcr/_core/model/predict.py
debcr/_core/model/train.py
debcr/_core/model/utils.py
debcr/_core/whole_img_tester.py
debcr/config.py
debcr/data.py
debcr/model.py
debcr-0.1.0.dist-info/LICENSE
debcr-0.1.0.dist-info/METADATA
debcr-0.1.0.dist-info/WHEEL
debcr-0.1.0.dist-info/RECORD
