Metadata-Version: 2.3
Name: debcr
Version: 0.1.0
Summary: Image enhancement framework for light microscopy data using deep learning.
License: MIT
Keywords: image processing,image restoration,image enhancement,deep learning,BCR,BCR-Net,m-rBCR,denoising,deblurring,deconvolution,confocal microscopy,widefield microscopy,fluorescence microscopy,light microscopy
Author: Artsemi Yushkevich
Maintainer: Artsemi Yushkevich
Requires-Python: >=3.9,<3.12
Classifier: Development Status :: 2 - Pre-Alpha
Classifier: Environment :: GPU :: NVIDIA CUDA :: 11.7
Classifier: Operating System :: POSIX :: Linux
Classifier: Programming Language :: Python
Classifier: Programming Language :: Python :: 3
Classifier: Programming Language :: Python :: 3.9
Classifier: Intended Audience :: Science/Research
Classifier: Topic :: Scientific/Engineering :: Image Processing
Provides-Extra: dev
Provides-Extra: tf-cpu
Provides-Extra: tf-gpu
Requires-Dist: PyYAML
Requires-Dist: matplotlib
Requires-Dist: natsort
Requires-Dist: numpy (==1.23.5)
Requires-Dist: pip ; extra == "dev"
Requires-Dist: scikit-image
Requires-Dist: setuptools ; extra == "dev"
Requires-Dist: tensorflow-cpu (==2.11) ; extra == "tf-cpu"
Requires-Dist: tensorflow-gpu (==2.11) ; extra == "tf-gpu"
Requires-Dist: tifffile
Project-URL: Homepage, https://github.com/DeBCR/DeBCR
